pyre.libs/libjournal-2f524770.so
pyre.libs/libpyre-647f0913.so
pyre-1.12.5.data/data/lib/python3.9/site-packages/merlin/__init__.py
pyre-1.12.5.data/data/lib/python3.9/site-packages/merlin/exceptions.py
pyre-1.12.5.data/data/lib/python3.9/site-packages/merlin/meta.py
pyre-1.12.5.data/data/lib/python3.9/site-packages/merlin/languages/__init__.py
pyre-1.12.5.data/data/lib/python3.9/site-packages/merlin/languages/CXX.py
pyre-1.12.5.data/data/lib/python3.9/site-packages/merlin/languages/Table.py
pyre-1.12.5.data/data/lib/python3.9/site-packages/merlin/languages/FORTRAN.py
pyre-1.12.5.data/data/lib/python3.9/site-packages/merlin/languages/Cython.py
pyre-1.12.5.data/data/lib/python3.9/site-packages/merlin/languages/C.py
pyre-1.12.5.data/data/lib/python3.9/site-packages/merlin/languages/Autogen.py
pyre-1.12.5.data/data/lib/python3.9/site-packages/merlin/languages/Python.py
pyre-1.12.5.data/data/lib/python3.9/site-packages/merlin/languages/CUDA.py
pyre-1.12.5.data/data/lib/python3.9/site-packages/merlin/languages/Language.py
pyre-1.12.5.data/data/lib/python3.9/site-packages/merlin/cli/__init__.py
pyre-1.12.5.data/data/lib/python3.9/site-packages/merlin/cli/Help.py
pyre-1.12.5.data/data/lib/python3.9/site-packages/merlin/cli/About.py
pyre-1.12.5.data/data/lib/python3.9/site-packages/merlin/cli/Complete.py
pyre-1.12.5.data/data/lib/python3.9/site-packages/merlin/cli/Libraries.py
pyre-1.12.5.data/data/lib/python3.9/site-packages/merlin/cli/Debug.py
pyre-1.12.5.data/data/lib/python3.9/site-packages/merlin/cli/Info.py
pyre-1.12.5.data/data/lib/python3.9/site-packages/merlin/cli/Build.py
pyre-1.12.5.data/data/lib/python3.9/site-packages/merlin/cli/Config.py
pyre-1.12.5.data/data/lib/python3.9/site-packages/merlin/scs/__init__.py
pyre-1.12.5.data/data/lib/python3.9/site-packages/merlin/scs/Git.py
pyre-1.12.5.data/data/lib/python3.9/site-packages/merlin/builders/__init__.py
pyre-1.12.5.data/data/lib/python3.9/site-packages/merlin/builders/Builder.py
pyre-1.12.5.dist-info/WHEEL
pyre-1.12.5.dist-info/top_level.txt
pyre-1.12.5.dist-info/RECORD
pyre-1.12.5.dist-info/METADATA
pyre-1.12.5.dist-info/LICENSE
