Metadata-Version: 2.1
Name: pyre
Version: 1.12.5
Summary: A framework for building scientific applications
Author-email: "Michael A.G. Aïvázis" <michael.aivazis@para-sim.com>
Maintainer-email: "Michael A.G. Aïvázis" <michael.aivazis@para-sim.com>
Keywords: science,framework
Classifier: Development Status :: 6 - Mature
Classifier: License :: OSI Approved :: BSD License
Classifier: Programming Language :: Python :: 3 :: Only
Classifier: Programming Language :: Python :: 3.7
Classifier: Programming Language :: Python :: 3.8
Classifier: Programming Language :: Python :: 3.9
Classifier: Programming Language :: Python :: 3.10
Classifier: Programming Language :: Python :: 3.11
Requires-Python: >3.7.2
License-File: LICENSE
Requires-Dist: PyYAML
